expressgpt/__init__.py
expressgpt/expressgpt.py
expressgpt-0.1.2.dist-info/METADATA
expressgpt-0.1.2.dist-info/WHEEL
expressgpt-0.1.2.dist-info/entry_points.txt
expressgpt-0.1.2.dist-info/top_level.txt
expressgpt-0.1.2.dist-info/RECORD
