Metadata-Version: 2.1
Name: expressgpt
Version: 0.1.2
Summary: Run chatGPT anywhere
Author: Digant Patel
Author-email: pateldigant95@gmail.com
Classifier: Development Status :: 4 - Beta
Classifier: Intended Audience :: End Users/Desktop
Classifier: License :: OSI Approved :: GNU General Public License (GPL)
Classifier: Operating System :: OS Independent
Classifier: Programming Language :: Python :: 3
Requires-Dist: pynput
Requires-Dist: pyautogui
Requires-Dist: openai
Requires-Dist: colorama
